dante_tokenizer/__init__.py
dante_tokenizer/apps/__init__.py
dante_tokenizer/apps/csv_to_conllu.py
dante_tokenizer/apps/eval_tokenizers.py
dante_tokenizer/apps/txt_to_conllu.py
dante_tokenizer/data/__init__.py
dante_tokenizer/data/load.py
dante_tokenizer/data/preprocessing.py
dante_tokenizer/evaluate/__init__.py
dante_tokenizer/evaluate/evaluate.py
dante_tokenizer/tokenizer/__init__.py
dante_tokenizer/tokenizer/tokenizer.py
dante_tokenizer-0.2.0.dist-info/LICENSE
dante_tokenizer-0.2.0.dist-info/METADATA
dante_tokenizer-0.2.0.dist-info/WHEEL
dante_tokenizer-0.2.0.dist-info/top_level.txt
dante_tokenizer-0.2.0.dist-info/RECORD
