Metadata-Version: 2.1
Name: dante-tokenizer
Version: 0.2.0
Summary: UNKNOWN
Home-page: https://github.com/huberemanuel/twitter-portuguese-tokenizer
Author: Emanuel Huber
Author-email: emanuel.huber@usp.br
License: Apache 2.0
Download-URL: https://github.com/huberemanuel/twitter-portuguese-tokenizer/archive/refs/tags/v0.1-alpha.tar.gz
Keywords: tokenizer,twitter,portuguese
Platform: UNKNOWN
Requires-Dist: nltk (>=3.6.2)
Requires-Dist: regex (>=2021.4.4)
